Workbook

Sheet Dashboard
B2: E-COMMERCE SALES & PROFIT DASHBOARD
B5: Total Sales | D5: Total Profit | F5: Total Orders | H5: Avg Order Value
B8: =Analysis!B4 | D8: =Analysis!B5 | F8: =Analysis!B6 | H8: =Analysis!B8

Sheet Raw Data
A1: Order ID | B1: Order Date | C1: Customer Name | D1: Category | E1: Product | F1: Region | G1: State | H1: Quantity | I1: Unit Price | J1: Discount | K1: Sales | L1: Profit | M1: Payment Mode
A2: ORD100001 | B2: 45985 | C2: Priya Singh 36 | D2: Electronics | E2: Laptop | F2: West | G2: Gujarat | H2: 1 | I2: 89348 | J2: 0.25 | K2: 67011 | L2: 4936.73 | M2: UPI
A3: ORD100002 | B3: 45960 | C3: Priya Singh 60 | D3: Home & Kitchen | E3: Mixer | F3: South | G3: Telangana | H3: 5 | I3: 7431 | J3: 0 | K3: 37155 | L3: 6700.15 | M3: Net Banking
A4: ORD100003 | B4: 45872 | C4: Manish Yadav 41 | D4: Furniture | E4: Table Lamp | F4: West | G4: Maharashtra | H4: 4 | I4: 3287 | J4: 0.1 | K4: 11833.2 | L4: 2120.24 | M4: Debit Card
A5: ORD100004 | B5: 45710 | C5: Pooja Shah 89 | D5: Electronics | E5: Monitor | F5: South | G5: Karnataka | H5: 5 | I5: 16667 | J5: 0 | K5: 83335 | L5: 13379.55 | M5: Net Banking
A6: ORD100005 | B6: 45721 | C6: Neha Gupta 50 | D6: Home & Kitchen | E6: Mixer | F6: West | G6: Goa | H6: 1 | I6: 2875 | J6: 0.25 | K6: 2156.25 | L6: 145.03 | M6: Debit Card
A7: ORD100006 | B7: 45698 | C7: Kavya Nair 163 | D7: Furniture | E7: Office Chair | F7: East | G7: Bihar | H7: 3 | I7: 10329 | J7: 0.1 | K7: 27888.3 | L7: 5130.39 | M7: Debit Card
A8: ORD100007 | B8: 46017 | C8: Divya Iyer 63 | D8: Electronics | E8: Keyboard | F8: North | G8: Rajasthan | H8: 2 | I8: 4486 | J8: 0.15 | K8: 7626.2 | L8: 773.81 | M8: Net Banking
A9: ORD100008 | B9: 45770 | C9: Manish Yadav 81 | D9: Office Supplies | E9: Notebook | F9: North | G9: Delhi | H9: 4 | I9: 187 | J9: 0 | K9: 748 | L9: 31.96 | M9: Net Banking
A10: ORD100009 | B10: 45819 | C10: Rahul Kumar 68 | D10: Furniture | E10: Table Lamp | F10: East | G10: Jharkhand | H10: 2 | I10: 2520 | J10: 0.25 | K10: 3780 | L10: 513.12 | M10: Debit Card
A11: ORD100010 | B11: 45957 | C11: Priya Singh 36 | D11: Home & Kitchen | E11: Storage Box | F11: East | G11: Bihar | H11: 5 | I11: 2421 | J11: 0 | K11: 12105 | L11: 2230.06 | M11: UPI
A12: ORD100011 | B12: 45736 | C12: Arjun Verma 153 | D12: Furniture | E12: Table Lamp | F12: South | G12: Tamil Nadu | H12: 4 | I12: 4834 | J12: 0.1 | K12: 17402.4 | L12: 3313.66 | M12: UPI
A13: ORD100012 | B13: 46006 | C13: Ananya Reddy 76 | D13: Electronics | E13: Keyboard | F13: West | G13: Goa | H13: 4 | I13: 1995 | J13: 0.15 | K13: 6783 | L13: 629.82 | M13: Debit Card
... A10001: ORD110000 | B10001: 45948 | C10001: Manish Yadav 177 | D10001: Home & Kitchen | E10001: Water Bottle | F10001: East | G10001: Jharkhand | H10001: 4 | I10001: 879 | J10001: 0.05 | K10001: 3340.2 | L10001: 565.15 | M10001: Credit Card

Sheet Analysis
A1: E-Commerce Sales Analysis
A3: KPI | B3: Value | D3: Category | E3: Sales | F3: Profit | H3: Region | I3: Sales | J3: Profit
A4: Total Sales | B4: =SUM('Raw Data'!K2:K10001) | D4: Electronics | E4: =SUMIF('Raw Data'!D:D,D4,'Raw Data'!K:K) | F4: =SUMIF('Raw Data'!D:D,D4,'Raw Data'!L:L) | H4: South | I4: =SUMIF('Raw Data'!F:F,H4,'Raw Data'!K:K) | J4: =SUMIF('Raw Data'!F:F,H4,'Raw Data'!L:L)
A5: Total Profit | B5: =SUM('Raw Data'!L2:L10001) | D5: Furniture | E5: =SUMIF('Raw Data'!D:D,D5,'Raw Data'!K:K) | F5: =SUMIF('Raw Data'!D:D,D5,'Raw Data'!L:L) | H5: North | I5: =SUMIF('Raw Data'!F:F,H5,'Raw Data'!K:K) | J5: =SUMIF('Raw Data'!F:F,H5,'Raw Data'!L:L)
A6: Total Orders | B6: =COUNTA('Raw Data'!A2:A10001) | D6: Office Supplies | E6: =SUMIF('Raw Data'!D:D,D6,'Raw Data'!K:K) | F6: =SUMIF('Raw Data'!D:D,D6,'Raw Data'!L:L) | H6: West | I6: =SUMIF('Raw Data'!F:F,H6,'Raw Data'!K:K) | J6: =SUMIF('Raw Data'!F:F,H6,'Raw Data'!L:L)
A7: Total Quantity | B7: =SUM('Raw Data'!H2:H10001) | D7: Home & Kitchen | E7: =SUMIF('Raw Data'!D:D,D7,'Raw Data'!K:K) | F7: =SUMIF('Raw Data'!D:D,D7,'Raw Data'!L:L) | H7: East | I7: =SUMIF('Raw Data'!F:F,H7,'Raw Data'!K:K) | J7: =SUMIF('Raw Data'!F:F,H7,'Raw Data'!L:L)
A8: Average Order Value | B8: =B3/B5 | D8: Beauty | E8: =SUMIF('Raw Data'!D:D,D8,'Raw Data'!K:K) | F8: =SUMIF('Raw Data'!D:D,D8,'Raw Data'!L:L)
A9: Profit Margin | B9: =B4/B3
A13: Month | B13: Sales | C13: Profit
A14: 45658 | B14: =SUMIFS('Raw Data'!K:K,'Raw Data'!B:B,">="&A14,'Raw Data'!B:B,"<"&EDATE(A14,1)) | C14: =SUMIFS('Raw Data'!L:L,'Raw Data'!B:B,">="&A14,'Raw Data'!B:B,"<"&EDATE(A14,1))
A15: 45689 | B15: =SUMIFS('Raw Data'!K:K,'Raw Data'!B:B,">="&A15,'Raw Data'!B:B,"<"&EDATE(A15,1)) | C15: =SUMIFS('Raw Data'!L:L,'Raw Data'!B:B,">="&A15,'Raw Data'!B:B,"<"&EDATE(A15,1))
A16: 45717 | B16: =SUMIFS('Raw Data'!K:K,'Raw Data'!B:B,">="&A16,'Raw Data'!B:B,"<"&EDATE(A16,1)) | C16: =SUMIFS('Raw Data'!L:L,'Raw Data'!B:B,">="&A16,'Raw Data'!B:B,"<"&EDATE(A16,1))
A17: 45748 | B17: =SUMIFS('Raw Data'!K:K,'Raw Data'!B:B,">="&A17,'Raw Data'!B:B,"<"&EDATE(A17,1)) | C17: =SUMIFS('Raw Data'!L:L,'Raw Data'!B:B,">="&A17,'Raw Data'!B:B,"<"&EDATE(A17,1))
A18: 45778 | B18: =SUMIFS('Raw Data'!K:K,'Raw Data'!B:B,">="&A18,'Raw Data'!B:B,"<"&EDATE(A18,1)) | C18: =SUMIFS('Raw Data'!L:L,'Raw Data'!B:B,">="&A18,'Raw Data'!B:B,"<"&EDATE(A18,1))
A19: 45809 | B19: =SUMIFS('Raw Data'!K:K,'Raw Data'!B:B,">="&A19,'Raw Data'!B:B,"<"&EDATE(A19,1)) | C19: =SUMIFS('Raw Data'!L:L,'Raw Data'!B:B,">="&A19,'Raw Data'!B:B,"<"&EDATE(A19,1))
A20: 45839 | B20: =SUMIFS('Raw Data'!K:K,'Raw Data'!B:B,">="&A20,'Raw Data'!B:B,"<"&EDATE(A20,1)) | C20: =SUMIFS('Raw Data'!L:L,'Raw Data'!B:B,">="&A20,'Raw Data'!B:B,"<"&EDATE(A20,1))
A21: 45870 | B21: =SUMIFS('Raw Data'!K:K,'Raw Data'!B:B,">="&A21,'Raw Data'!B:B,"<"&EDATE(A21,1)) | C21: =SUMIFS('Raw Data'!L:L,'Raw Data'!B:B,">="&A21,'Raw Data'!B:B,"<"&EDATE(A21,1))
A22: 45901 | B22: =SUMIFS('Raw Data'!K:K,'Raw Data'!B:B,">="&A22,'Raw Data'!B:B,"<"&EDATE(A22,1)) | C22: =SUMIFS('Raw Data'!L:L,'Raw Data'!B:B,">="&A22,'Raw Data'!B:B,"<"&EDATE(A22,1))
A23: 45931 | B23: =SUMIFS('Raw Data'!K:K,'Raw Data'!B:B,">="&A23,'Raw Data'!B:B,"<"&EDATE(A23,1)) | C23: =SUMIFS('Raw Data'!L:L,'Raw Data'!B:B,">="&A23,'Raw Data'!B:B,"<"&EDATE(A23,1))
A24: 45962 | B24: =SUMIFS('Raw Data'!K:K,'Raw Data'!B:B,">="&A24,'Raw Data'!B:B,"<"&EDATE(A24,1)) | C24: =SUMIFS('Raw Data'!L:L,'Raw Data'!B:B,">="&A24,'Raw Data'!B:B,"<"&EDATE(A24,1))
A25: 45992 | B25: =SUMIFS('Raw Data'!K:K,'Raw Data'!B:B,">="&A25,'Raw Data'!B:B,"<"&EDATE(A25,1)) | C25: =SUMIFS('Raw Data'!L:L,'Raw Data'!B:B,">="&A25,'Raw Data'!B:B,"<"&EDATE(A25,1))

Sheet Project Guide
A1: PROJECT GUIDE
A3: Project | B3: E-Commerce Sales & Profitability Analysis Dashboard
A4: Objective | B4: Analyze sales, profit, orders, product categories, regions and monthly trends using Excel.
A5: Tools | B5: Microsoft Excel, Tables, SUMIF/SUMIFS, Pivot-style analysis, charts and dashboard design.
A6: Dataset | B6: 10,000 synthetic e-commerce transactions covering January–December 2025.
A7: Key Questions | B7: Which categories generate the most sales? Which regions are most profitable? How do sales change monthly?
A8: Business Insights | B8: Use the dashboard to identify high-performing categories, regions and months, and evaluate profit impact.
A9: Portfolio Skills | B9: Data preparation, formulas, KPI reporting, business analysis, visualization and dashboard storytelling.
A10: How to Use | B10: Start with Dashboard. Raw Data contains transactions. Analysis contains calculation tables used by the dashboard.
